odoo/addons/web_widget_pattern/README.rst
odoo/addons/web_widget_pattern/__init__.py
odoo/addons/web_widget_pattern/__manifest__.py
odoo/addons/web_widget_pattern/demo/res_partner_views.xml
odoo/addons/web_widget_pattern/i18n/it.po
odoo/addons/web_widget_pattern/i18n/web_widget_pattern.pot
odoo/addons/web_widget_pattern/models/__init__.py
odoo/addons/web_widget_pattern/models/base.py
odoo/addons/web_widget_pattern/readme/CONTRIBUTORS.md
odoo/addons/web_widget_pattern/readme/DESCRIPTION.md
odoo/addons/web_widget_pattern/readme/ROADMAP.md
odoo/addons/web_widget_pattern/readme/USAGE.md
odoo/addons/web_widget_pattern/static/description/icon.png
odoo/addons/web_widget_pattern/static/description/index.html
odoo/addons/web_widget_pattern/static/src/autocomplete.esm.js
odoo/addons/web_widget_pattern/static/src/autocomplete.xml
odoo/addons/web_widget_pattern/static/src/char_field.esm.js
odoo/addons/web_widget_pattern/static/src/char_field.xml
odoo/addons/web_widget_pattern/tests/__init__.py
odoo/addons/web_widget_pattern/tests/test_web_widget_pattern.py
odoo_addon_web_widget_pattern-16.0.1.0.0.3.dist-info/METADATA
odoo_addon_web_widget_pattern-16.0.1.0.0.3.dist-info/WHEEL
odoo_addon_web_widget_pattern-16.0.1.0.0.3.dist-info/top_level.txt
odoo_addon_web_widget_pattern-16.0.1.0.0.3.dist-info/RECORD
